{"document_id":"320001131990","content":"Consignee: LUCKY OPCO LLC | Current shipment status: AT_ORIGIN\n\nParties & service: Consignee: LUCKY OPCO LLC | Ship-to party: RADIAL RICHWOOD(0044435) | Supplier\/Vendor: TEXPIA 3(0039373) | Manufacturer: TEXPIA 3(0044675) | Job type: OCB | Destination service: CY | Transport mode: SEA | Hot container flag: False | Booking approval status: APPROVED(GT3000514)\n\nRouting & movements: Origin: PUERTO QUETZAL(GTPRQ) | Load Port: PUERTO QUETZAL(GTPRQ) | Discharge Port: LONG BEACH, CA(USLGB) | Place of Delivery: LONG BEACH, CA(USLGB) | Final Destination: SHEPHERDSVILLE, KY(USSQN) || Route summary: Origin: PUERTO QUETZAL(GTPRQ) -> Discharge Port: LONG BEACH, CA(USLGB) -> Final: SHEPHERDSVILLE, KY(USSQN) || Vessel summary: First vessel: AS PALINA || Carrier summary: Operated by MAERSK SEALAND\n\nReferences: PO Numbers: 2K79800, 2K79900, 2K80000, 2K87700, 2K87800, 2K87900, 2K88000, 2K88100, 2K88200, 2K89000 | Booking Numbers: GT3000514, GT3000514 | Service contract number: 297368942(GT3000514)\n\nStatus & timeline: DP delay status: on_time, Δ≈0 day(s). | FD delay status: on_time, Δ≈0 day(s). || Milestones: Overall shipment status: AT_ORIGIN || Leg 1 (POR → Load Port) [PLANNED]: PUERTO QUETZAL(GTPRQ) → PUERTO QUETZAL(GTPRQ); planned ETD 2026-01-13 from PUERTO QUETZAL(GTPRQ). || Leg 2 (Load Port → TS) [NOT_APPLICABLE]: no transshipment; direct ocean leg from PUERTO QUETZAL(GTPRQ) to LONG BEACH, CA(USLGB). || Leg 3 (TS → Discharge Port) [IN_PROGRESS]: PUERTO QUETZAL(GTPRQ) → LONG BEACH, CA(USLGB); in ocean transit towards LONG BEACH, CA(USLGB) (ETA DP 2026-01-23). || Leg 4 (DP → Last CY) [PLANNED]: LONG BEACH, CA(USLGB) → Last CY; no DP→CY movement recorded yet. || Leg 5 (Last CY → Final) [PLANNED]: Last CY → SHEPHERDSVILLE, KY(USSQN); delivery and empty container return pending; ETA FD 2026-02-04. || Critical dates: Stage 1 (POR → Load Port): PUERTO QUETZAL(GTPRQ) → PUERTO QUETZAL(GTPRQ) (ETD=2026-01-13, ATD=N\/A; departure scheduled; actual not yet recorded) || Stage 2 (Load Port → TS): no transshipment; direct ocean leg from PUERTO QUETZAL(GTPRQ) to LONG BEACH, CA(USLGB) || Stage 3 (TS → Discharge Port): PUERTO QUETZAL(GTPRQ) → LONG BEACH, CA(USLGB) (ETA DP=2026-01-23, ATA DP=N\/A, on time) || Stage 4 (DP → Last CY): LONG BEACH, CA(USLGB) → Last CY (no clear DP→CY movement recorded) || Stage 5 (Last CY → Final): Last CY → SHEPHERDSVILLE, KY(USSQN) (ETA FD=2026-02-04, delivery still upcoming based on ETA FD; on time) || Delay analysis: Shipment is on time against configured DP \/ final destination ETAs.\n\nCargo & CO2: Cargo metrics: weight 711.55 kg volume 5.03 m3 | Cargo count: 255 PCS | Detail cargo: 3076 PCS","metadata":{"job_no":"GT3LBD2601001","container_number":null,"container_type":"S2","destination_service":"CY","consignee_raw":"LUCKY OPCO LLC(0043882)","po_numbers":"2K79800, 2K79900, 2K80000, 2K87700, 2K87800, 2K87900, 2K88000, 2K88100, 2K88200, 2K89000","booking_numbers":"GT3000514, GT3000514","fcr_numbers":null,"obl_nos":"","load_port":"PUERTO QUETZAL(GTPRQ)","final_load_port":null,"discharge_port":"LONG BEACH, CA(USLGB)","last_cy_location":null,"place_of_receipt":"PUERTO QUETZAL(GTPRQ)","place_of_delivery":"LONG BEACH, CA(USLGB)","final_destination":"SHEPHERDSVILLE, KY(USSQN)","first_vessel_name":"AS PALINA","final_carrier_name":"MAERSK SEALAND","final_vessel_name":"AS PALINA","true_carrier_scac_name":"MAERSK SEALAND","etd_lp_date":"2026-01-13","etd_flp_date":null,"eta_dp_date":"2026-01-23","atd_lp_date":null,"ata_flp_date":null,"atd_flp_date":null,"derived_ata_dp_date":"2026-01-23","cargo_receiveds_date":null,"detention_free_days":"7","demurrage_free_days":"7","hot_container_flag":false,"supplier_vendor_name":"TEXPIA 3(0039373)","manufacturer_name":"TEXPIA 3(0044675)","ship_to_party_name":"RADIAL RICHWOOD(0044435)","booking_approval_status":"APPROVED(GT3000514)","service_contract_number":"297368942(GT3000514)","carrier_vehicle_load_date":null,"carrier_vehicle_load_lcn":null,"vehicle_departure_date":null,"vehicle_departure_lcn":null,"vehicle_arrival_date":null,"vehicle_arrival_lcn":null,"carrier_vehicle_unload_date":null,"carrier_vehicle_unload_lcn":null,"out_gate_from_dp_date":null,"out_gate_from_dp_lcn":null,"equipment_arrived_at_last_cy_date":null,"equipment_arrived_at_last_cy_lcn":null,"out_gate_at_last_cy_date":null,"out_gate_at_last_cy_lcn":null,"delivery_to_consignee_date":null,"delivery_to_consignee_lcn":null,"empty_container_return_date":null,"empty_container_return_lcn":null,"co2_tank_on_wheel":null,"co2_well_to_wheel":null,"job_type":"OCB","mcs_hbl":null,"transport_mode":"SEA","rail_load_dp_date":null,"rail_load_dp_lcn":null,"rail_departure_dp_date":null,"rail_departure_dp_lcn":null,"rail_arrival_destination_date":null,"rail_arrival_destination_lcn":null,"cargo_weight_kg":"711.55","cargo_measure_cubic_meter":"5.03","cargo_count":"255","cargo_um":"PCS","cargo_detail_count":"3076","detail_cargo_um":"PCS","consignee_name":"LUCKY OPCO LLC","consignee_codes":["0043882"],"optimal_ata_dp_date":null,"optimal_eta_fd_date":"2026-02-04","shipment_status":"AT_ORIGIN","vessel_summary":"First vessel: AS PALINA","carrier_summary":"Operated by MAERSK SEALAND","port_route_summary":"Origin: PUERTO QUETZAL(GTPRQ) -> Discharge Port: LONG BEACH, CA(USLGB) -> Final: SHEPHERDSVILLE, KY(USSQN)","delayed_dp":"on_time","dp_delayed_dur":0.0,"delayed_fd":"on_time","fd_delayed_dur":0.0,"critical_dates_summary":"Stage 1 (POR → Load Port): PUERTO QUETZAL(GTPRQ) → PUERTO QUETZAL(GTPRQ) (ETD=2026-01-13, ATD=N\/A; departure scheduled; actual not yet recorded) || Stage 2 (Load Port → TS): no transshipment; direct ocean leg from PUERTO QUETZAL(GTPRQ) to LONG BEACH, CA(USLGB) || Stage 3 (TS → Discharge Port): PUERTO QUETZAL(GTPRQ) → LONG BEACH, CA(USLGB) (ETA DP=2026-01-23, ATA DP=N\/A, on time) || Stage 4 (DP → Last CY): LONG BEACH, CA(USLGB) → Last CY (no clear DP→CY movement recorded) || Stage 5 (Last CY → Final): Last CY → SHEPHERDSVILLE, KY(USSQN) (ETA FD=2026-02-04, delivery still upcoming based on ETA FD; on time)","delay_reason_summary":"Shipment is on time against configured DP \/ final destination ETAs.","workflow_gap_flags":"none_detected","milestones":"Overall shipment status: AT_ORIGIN || Leg 1 (POR → Load Port) [PLANNED]: PUERTO QUETZAL(GTPRQ) → PUERTO QUETZAL(GTPRQ); planned ETD 2026-01-13 from PUERTO QUETZAL(GTPRQ). || Leg 2 (Load Port → TS) [NOT_APPLICABLE]: no transshipment; direct ocean leg from PUERTO QUETZAL(GTPRQ) to LONG BEACH, CA(USLGB). || Leg 3 (TS → Discharge Port) [IN_PROGRESS]: PUERTO QUETZAL(GTPRQ) → LONG BEACH, CA(USLGB); in ocean transit towards LONG BEACH, CA(USLGB) (ETA DP 2026-01-23). || Leg 4 (DP → Last CY) [PLANNED]: LONG BEACH, CA(USLGB) → Last CY; no DP→CY movement recorded yet. || Leg 5 (Last CY → Final) [PLANNED]: Last CY → SHEPHERDSVILLE, KY(USSQN); delivery and empty container return pending; ETA FD 2026-02-04.","source_month_tag":"jan26","source_group":"shipment_jan26"},"consignee_code":"['0043882']"}
